agentfc/__init__.py
agentfc/collector.py
agentfc/facedet.py
AgentFC-0.4.dist-info/LICENSE
AgentFC-0.4.dist-info/METADATA
AgentFC-0.4.dist-info/WHEEL
AgentFC-0.4.dist-info/top_level.txt
AgentFC-0.4.dist-info/RECORD
