Metadata-Version: 2.1
Name: AgentFC
Version: 0.4
Summary: 人像变换辅助工具
Home-page: https://github.com/AgentMaker/AgentFaceCollector
Author: AgentMaker
Author-email: agentmaker@163.com
License: Apache2
Platform: UNKNOWN
Requires-Python: >3.6
License-File: LICENSE
Requires-Dist: opencv-python
Requires-Dist: paddlehub
